recipes/__init__.py
recipes/eleuther_eval.py
recipes/full_finetune_distributed.py
recipes/full_finetune_single_device.py
recipes/generate.py
recipes/lora_dpo_distributed.py
recipes/lora_dpo_single_device.py
recipes/lora_finetune_distributed.py
recipes/lora_finetune_single_device.py
recipes/quantize.py
recipes/configs/eleuther_evaluation.yaml
recipes/configs/generation.yaml
recipes/configs/quantization.yaml
recipes/configs/code_llama2/7B_full_low_memory.yaml
recipes/configs/code_llama2/7B_lora_single_device.yaml
recipes/configs/code_llama2/7B_qlora_single_device.yaml
recipes/configs/dev/8B_full_experimental.yaml
recipes/configs/gemma/2B_full.yaml
recipes/configs/gemma/2B_lora.yaml
recipes/configs/gemma/2B_lora_single_device.yaml
recipes/configs/gemma/2B_qlora_single_device.yaml
recipes/configs/gemma/7B_full.yaml
recipes/configs/gemma/7B_lora.yaml
recipes/configs/gemma/7B_lora_single_device.yaml
recipes/configs/gemma/7B_qlora_single_device.yaml
recipes/configs/llama2/13B_full.yaml
recipes/configs/llama2/13B_lora.yaml
recipes/configs/llama2/13B_qlora_single_device.yaml
recipes/configs/llama2/70B_lora.yaml
recipes/configs/llama2/7B_full.yaml
recipes/configs/llama2/7B_full_low_memory.yaml
recipes/configs/llama2/7B_lora.yaml
recipes/configs/llama2/7B_lora_dpo.yaml
recipes/configs/llama2/7B_lora_dpo_single_device.yaml
recipes/configs/llama2/7B_lora_single_device.yaml
recipes/configs/llama2/7B_qlora_single_device.yaml
recipes/configs/llama3/70B_full.yaml
recipes/configs/llama3/70B_lora.yaml
recipes/configs/llama3/8B_full.yaml
recipes/configs/llama3/8B_full_single_device.yaml
recipes/configs/llama3/8B_lora.yaml
recipes/configs/llama3/8B_lora_single_device.yaml
recipes/configs/llama3/8B_qlora_single_device.yaml
recipes/configs/mistral/7B_full.yaml
recipes/configs/mistral/7B_full_low_memory.yaml
recipes/configs/mistral/7B_lora.yaml
recipes/configs/mistral/7B_lora_single_device.yaml
recipes/configs/mistral/7B_qlora_single_device.yaml
recipes/configs/phi3/mini_full.yaml
forked_torchtune-0.0.0.dist-info/LICENSE
forked_torchtune-0.0.0.dist-info/METADATA
forked_torchtune-0.0.0.dist-info/WHEEL
forked_torchtune-0.0.0.dist-info/entry_points.txt
forked_torchtune-0.0.0.dist-info/top_level.txt
forked_torchtune-0.0.0.dist-info/RECORD
