Metadata-Version: 2.1
Name: forked-torchtune
Version: 0.0.0
Summary: A native-PyTorch library for LLM fine-tuning
Author-email: PyTorch Team <packages@pytorch.org>
License: BSD 3-Clause License
Project-URL: GitHub, https://github.com/pytorch/torchtune
Project-URL: Documentation, https://pytorch.org/torchtune/main/index.html
Project-URL: Issues, https://github.com/pytorch/torchtune/issues
Keywords: pytorch,finetuning,llm
Requires-Python: >=3.8
License-File: LICENSE
Requires-Dist: datasets
Requires-Dist: huggingface-hub
Requires-Dist: safetensors
Requires-Dist: sentencepiece
Requires-Dist: tiktoken
Requires-Dist: blobfile >=2
Requires-Dist: tqdm
Requires-Dist: omegaconf
Requires-Dist: torchao ==0.1
Provides-Extra: dev
Requires-Dist: bitsandbytes >=0.43.0 ; extra == 'dev'
Requires-Dist: pre-commit ; extra == 'dev'
Requires-Dist: pytest ==7.4.0 ; extra == 'dev'
Requires-Dist: pytest-cov ; extra == 'dev'
Requires-Dist: pytest-mock ; extra == 'dev'
Requires-Dist: pytest-integration ; extra == 'dev'
Requires-Dist: tensorboard ; extra == 'dev'
Requires-Dist: wandb ; extra == 'dev'
Requires-Dist: expecttest ; extra == 'dev'
